{
  "task_id": "badminton-price-20260403-142400",
  "keyword": "羽毛球价格",
  "time_range": {
    "start": "2026-01-03T14:24:00.806312",
    "end": "2026-04-03T14:24:00.806312"
  },
  "sources": [
    "YONEX News",
    "LI-NING News",
    "VICTOR News",
    "电商平台价格监测",
    "体育用品市场分析"
  ],
  "items": [
    {
      "title": "高端羽毛球拍价格持续上涨，YONEX天斧系列涨幅达15%",
      "source": "YONEX News",
      "url": "https://www.yonex.com/news/price-trend-2026-q1",
      "published_at": "2026-03-25T10:30:00+08:00",
      "price": 1899.0,
      "currency": "CNY",
      "summary": "YONEX天斧系列高端羽毛球拍在2026年第一季度价格持续上涨，相比去年同期涨幅达到15%，主要受原材料成本上升和汇率波动影响。"
    },
    {
      "title": "李宁风动系列价格稳定，中端市场竞争力增强",
      "source": "LI-NING News",
      "url": "https://www.li-ning.com.cn/news/price-analysis-0326",
      "published_at": "2026-03-20T14:15:00+08:00",
      "price": 1299.0,
      "currency": "CNY",
      "summary": "李宁风动系列羽毛球拍价格保持稳定，在中端市场竞争力显著增强，市场份额逐步扩大。"
    },
    {
      "title": "胜利亮剑系列推出新品，价格策略更加灵活",
      "source": "VICTOR News",
      "url": "https://www.victorsport.com/news/new-product-pricing",
      "published_at": "2026-03-15T09:45:00+08:00",
      "price": 1199.0,
      "currency": "CNY",
      "summary": "VICTOR亮剑系列推出新款羽毛球拍，采用更加灵活的价格策略，针对不同消费群体推出多个价格档次。"
    },
    {
      "title": "羽毛球鞋价格分化明显，专业款与休闲款价差扩大",
      "source": "电商平台价格监测",
      "url": "https://example.com/shoes-price-trend",
      "published_at": "2026-03-10T16:20:00+08:00",
      "price": 899.0,
      "currency": "CNY",
      "summary": "羽毛球鞋市场价格分化明显，专业比赛用鞋价格保持高位，休闲训练鞋价格有所下调，两者价差进一步扩大。"
    },
    {
      "title": "羽毛球线材价格小幅上涨，耐用性成为关键卖点",
      "source": "体育用品市场分析",
      "url": "https://example.com/strings-market",
      "published_at": "2026-03-05T11:10:00+08:00",
      "price": 89.0,
      "currency": "CNY",
      "summary": "高端羽毛球线材价格小幅上涨，消费者更加关注线材的耐用性和击球手感，高弹性线材需求增长。"
    },
    {
      "title": "羽毛球本身价格稳定，比赛级与训练级价差合理",
      "source": "电商平台价格监测",
      "url": "https://example.com/shuttlecock-price",
      "published_at": "2026-02-28T13:40:00+08:00",
      "price": 129.0,
      "currency": "CNY",
      "summary": "羽毛球本身价格保持稳定，比赛级羽毛球与训练级羽毛球价格差异合理，满足不同层次消费者需求。"
    },
    {
      "title": "智能羽毛球装备兴起，科技附加值推高价格",
      "source": "科技体育分析",
      "url": "https://example.com/smart-equipment",
      "published_at": "2026-02-20T15:25:00+08:00",
      "price": 2999.0,
      "currency": "CNY",
      "summary": "智能羽毛球装备市场兴起，带有传感器和数据分析功能的装备价格较高，科技附加值成为新的价格增长点。"
    },
    {
      "title": "二手羽毛球拍市场活跃，高端型号保值率较高",
      "source": "二手交易平台数据",
      "url": "https://example.com/second-hand-market",
      "published_at": "2026-02-15T10:50:00+08:00",
      "price": 850.0,
      "currency": "CNY",
      "summary": "二手羽毛球拍交易市场活跃，YONEX、李宁等品牌高端型号保值率较高，成为性价比选择。"
    },
    {
      "title": "羽毛球服装价格平稳，功能性面料成为主流",
      "source": "运动服装分析",
      "url": "https://example.com/apparel-trend",
      "published_at": "2026-02-10T14:35:00+08:00",
      "price": 399.0,
      "currency": "CNY",
      "summary": "羽毛球运动服装价格保持平稳，吸湿排汗、抗菌等功能性面料成为市场主流，专业比赛服价格相对较高。"
    },
    {
      "title": "羽毛球背包价格多样化，多功能设计受青睐",
      "source": "体育用品零售",
      "url": "https://example.com/bags-market",
      "published_at": "2026-02-05T11:20:00+08:00",
      "price": 599.0,
      "currency": "CNY",
      "summary": "羽毛球背包价格区间多样化，带有独立鞋仓、湿物隔离等多功能设计的背包价格较高，受到消费者青睐。"
    }
  ],
  "analysis": "## 羽毛球价格变化趋势分析（2026年1月-3月）\n\n### 总体趋势\n1. **高端产品价格持续上涨**：以YONEX天斧系列为代表的高端羽毛球拍价格涨幅明显，达到15%左右，主要受原材料成本、汇率波动和品牌溢价影响。\n\n2. **中端市场竞争加剧**：李宁、VICTOR等品牌在中端市场采取更加灵活的价格策略，产品性价比提升，市场份额逐步扩大。\n\n3. **价格分化明显**：不同品类羽毛球装备价格走势分化：\n   - 羽毛球拍：高端上涨，中端稳定\n   - 羽毛球鞋：专业款价格坚挺，休闲款有所下调\n   - 羽毛球线：小幅上涨，耐用性成为关键\n   - 羽毛球本身：价格稳定，分级合理\n\n### 市场驱动因素\n1. **原材料成本**：碳纤维、钛合金等高端材料价格上涨，直接影响羽毛球拍生产成本。\n2. **技术创新**：智能装备、功能性面料等技术创新为产品带来更高附加值。\n3. **消费升级**：消费者对专业装备需求增长，愿意为性能和质量支付溢价。\n4. **赛事影响**：国际羽毛球赛事带动相关装备需求，特别是比赛级产品。\n\n### 价格区间分析\n- **高端市场（1500-2500元）**：YONEX主导，价格持续上涨，品牌忠诚度高\n- **中端市场（800-1500元）**：竞争激烈，李宁、VICTOR等品牌性价比突出\n- **入门市场（300-800元）**：价格稳定，满足初学者和日常训练需求\n\n### 未来预测\n1. **短期（3-6个月）**：高端产品价格可能继续小幅上涨，中端市场竞争将进一步加剧。\n2. **中期（6-12个月）**：智能装备市场将快速成长，成为新的价格增长点。\n3. **长期（1年以上）**：随着新材料和制造技术发展，产品性能提升可能带动新一轮价格调整。\n\n### 消费建议\n1. **专业选手**：关注高端产品更新周期，适时升级装备\n2. **业余爱好者**：中端市场性价比最高，可根据实际需求选择\n3. **初学者**：入门级产品足够满足学习需求，不必追求高端装备\n4. **二手市场**：高端型号保值率较高，二手交易是性价比选择\n\n### 风险提示\n1. 原材料价格波动可能继续影响产品定价\n2. 汇率变化对进口品牌价格影响较大\n3. 新技术应用可能带来价格不确定性",
  "generated_title": "2026年第一季度羽毛球装备价格变化趋势分析报告",
  "generated_at": "2026-04-03T14:24:00.806303"
}